ConexionPSQL/__init__.py
ConexionPSQL-0.0.3.dist-info/LICENSE.txt
ConexionPSQL-0.0.3.dist-info/METADATA
ConexionPSQL-0.0.3.dist-info/WHEEL
ConexionPSQL-0.0.3.dist-info/top_level.txt
ConexionPSQL-0.0.3.dist-info/RECORD
