Metadata-Version: 2.1
Name: ConexionPSQL
Version: 0.0.3
Summary: Libreria para conectarse a bbdd postgresql
Home-page: https://cofeeblcks.com
Author: Hadik Chavez
Author-email: cofeeblcks@gmail.com
License: MIT
Classifier: Programming Language :: Python :: 3
Classifier: License :: OSI Approved :: MIT License
Classifier: Operating System :: OS Independent
Requires-Python: >=3.9
License-File: LICENSE.txt
Requires-Dist: psycopg2
